pygments_signalflow/__init__.py
pygments_signalflow-0.3.dist-info/DESCRIPTION.rst
pygments_signalflow-0.3.dist-info/METADATA
pygments_signalflow-0.3.dist-info/RECORD
pygments_signalflow-0.3.dist-info/WHEEL
pygments_signalflow-0.3.dist-info/entry_points.txt
pygments_signalflow-0.3.dist-info/metadata.json
pygments_signalflow-0.3.dist-info/pbr.json
pygments_signalflow-0.3.dist-info/top_level.txt
pygments_signalflow-0.3.dist-info/zip-safe
