Metadata-Version: 2.0
Name: pygments-signalflow
Version: 0.3
Summary: Pygments lexer for SignalFlow
Home-page: https://github.com/mpetazzoni/pygments-signalflow
Author: Maxime Petazzoni
Author-email: maxime.petazzoni@bulix.org
License: Apache Software License v2
Platform: UNKNOWN
Classifier: Environment :: Plugins
Classifier: Intended Audience :: Developers
Classifier: Operating System :: OS Independent
Classifier: Programming Language :: Python
Classifier: Programming Language :: Python :: 2
Classifier: Programming Language :: Python :: 3
Classifier: Topic :: Software Development :: Libraries :: Python Modules
Requires-Dist: pygments
